discovery/__init__.py
discovery/main.py
discovery/models.py
microstorm/__init__.py
microstorm/config.py
microstorm/discovery.py
microstorm/events.py
microstorm/messaging.py
microstorm/monitoring.py
microstorm/registry.py
microstorm/router.py
microstorm/security.py
microstorm/service.py
microstorm-0.1.2.dist-info/licenses/LICENSE
strictaccess/setup.py
microstorm-0.1.2.dist-info/METADATA
microstorm-0.1.2.dist-info/WHEEL
microstorm-0.1.2.dist-info/top_level.txt
microstorm-0.1.2.dist-info/RECORD
