Metadata-Version: 2.4
Name: microstorm
Version: 0.1.2
Summary: A modern microservices toolkit for Python with built-in discovery, metrics, and security.
Home-page: https://github.com/jhoelperaltap/microstorm
Author: Jhoel Peralta
Author-email: Jhoel Peralta <jhoelperalta@gmail.com>
License: MIT
Project-URL: Homepage, https://github.com/jhoelperaltap/microstorm
Project-URL: Documentation, https://github.com/jhoelperaltap/microstorm#readme
Project-URL: Source, https://github.com/jhoelperaltap/microstorm
Keywords: microservices,fastapi,prometheus,jwt,service discovery,microstorm
Classifier: Programming Language :: Python :: 3
Classifier: Framework :: FastAPI
Classifier: License :: OSI Approved :: MIT License
Classifier: Operating System :: OS Independent
Classifier: Intended Audience :: Developers
Classifier: Topic :: Software Development :: Libraries
Classifier: Topic :: Internet :: WWW/HTTP
Classifier: Topic :: Internet :: WWW/HTTP :: WSGI :: Application
Requires-Python: >=3.8
License-File: LICENSE
Requires-Dist: fastapi
Requires-Dist: uvicorn
Requires-Dist: httpx
Requires-Dist: prometheus_client
Requires-Dist: python-dotenv
Requires-Dist: PyJWT
Dynamic: author
Dynamic: home-page
Dynamic: license-file
Dynamic: requires-python
